pri/__init__.py
pri/__main__.py
pri/repositories.json
pri/version.py
pri-1.0.3.dist-info/DESCRIPTION.rst
pri-1.0.3.dist-info/METADATA
pri-1.0.3.dist-info/RECORD
pri-1.0.3.dist-info/WHEEL
pri-1.0.3.dist-info/entry_points.txt
pri-1.0.3.dist-info/metadata.json
pri-1.0.3.dist-info/top_level.txt
pri-1.0.3.dist-info/zip-safe
