Metadata-Version: 2.0
Name: pri
Version: 1.0.3
Summary: Pip Repository Manager. Switch PyPi mirror.
Home-page: https://github.com/xiyusullos/PipRepositoryIndex
Author: xiyusullos
Author-email: i@xy-jit.cc
License: MIT
Keywords: python,PyPi mirror,pip repository manager
Platform: any
Requires-Dist: docopt (==0.6.2)
